[
  {
    "id": "regular",
    "title": "নিয়মিত অনুদান",
    "description": "ফাউন্ডেশনের নিয়মিত শিক্ষা, সেবা ও মানবিক কার্যক্রম চালিয়ে নিতে মাসিক বা সুবিধামতো অনুদান দিন।",
    "icon": "Coins",
    "url": "/donate"
  },
  {
    "id": "zakat",
    "title": "যাকাত তহবিল",
    "description": "আপনার যাকাতের অর্থ শরিয়াহসম্মতভাবে দরিদ্র, অসহায় ও প্রকৃত হকদারদের কাছে পৌঁছে দিতে সহায়তা করুন।",
    "icon": "HeartHandshake",
    "url": "/donate"
  },
  {
    "id": "sadaqah-jariyah",
    "title": "সদকায়ে জারিয়া তহবিল",
    "description": "স্থায়ী নেক আমলের অংশ হিসেবে মসজিদ, মাদ্রাসা, পানি প্রকল্প ও কল্যাণমূলক কাজে অনুদান দিন।",
    "icon": "Droplets",
    "url": "/donate"
  },
  {
    "id": "student-sponsor",
    "title": "মেধাবী শিক্ষার্থী স্পন্সর",
    "description": "মেধাবী ও সুবিধাবঞ্চিত শিক্ষার্থীদের পড়াশোনা, শিক্ষা উপকরণ ও প্রয়োজনীয় সহায়তায় পাশে থাকুন।",
    "icon": "GraduationCap",
    "url": "/donate"
  },
  {
    "id": "skill-development",
    "title": "স্কিল ডেভেলপমেন্ট",
    "description": "বেকার যুবক ও সুবিধাবঞ্চিত মানুষদের কারিগরি, আইসিটি ও কর্মমুখী প্রশিক্ষণে সহায়তা করুন।",
    "icon": "BookOpen",
    "url": "/donate"
  },
  {
    "id": "self-reliance",
    "title": "স্বাবলম্বীকরণ তহবিল",
    "description": "দরিদ্র পরিবারকে কর্মসংস্থান, ক্ষুদ্র উদ্যোগ ও স্বনির্ভরতার পথে এগিয়ে নিতে অনুদান দিন।",
    "icon": "HandHeart",
    "url": "/donate"
  }
]
